Cross_Matching/Cross_Match.py
Cross_Matching/__init__.py
Cross_Matching-0.1.4.dist-info/DESCRIPTION.rst
Cross_Matching-0.1.4.dist-info/METADATA
Cross_Matching-0.1.4.dist-info/RECORD
Cross_Matching-0.1.4.dist-info/WHEEL
Cross_Matching-0.1.4.dist-info/metadata.json
Cross_Matching-0.1.4.dist-info/top_level.txt
