Metadata-Version: 2.0
Name: Cross-Matching
Version: 0.1.4
Summary: Cross Matching Astronomical Catalogues
Home-page: https://github.com/TrystanScottLambert/Cross_Matching
Author: Trystan Scott Lambert
Author-email: TrystanScottLambert@gmail.com
License: UNKNOWN
Platform: UNKNOWN
